pinliner/__init__.py
pinliner/importer.template
pinliner/pinliner.py
pinliner-0.2.0.dist-info/DESCRIPTION.rst
pinliner-0.2.0.dist-info/METADATA
pinliner-0.2.0.dist-info/RECORD
pinliner-0.2.0.dist-info/WHEEL
pinliner-0.2.0.dist-info/entry_points.txt
pinliner-0.2.0.dist-info/metadata.json
pinliner-0.2.0.dist-info/top_level.txt
