Metadata-Version: 2.0
Name: pinliner
Version: 0.2.0
Summary: Python Inliner merges in a single file all files from a Python package.
Home-page: https://github.com/Akrog/pinliner
Author: Gorka Eguileor
Author-email: gorka@eguileor.com
License: Apache
Keywords: pinliner
Platform: UNKNOWN
Classifier: Development Status :: 2 - Pre-Alpha
Classifier: Intended Audience :: Developers
Classifier: License :: OSI Approved :: Apache Software License
Classifier: Natural Language :: English
Classifier: Programming Language :: Python :: 2
Classifier: Programming Language :: Python :: 2.7
